[
  {
    "movieId": 747,
    "score": 1.0,
    "reason": "Hollywood snark and desperate heist of truth in romantic undercover"
  },
  {
    "movieId": 275,
    "score": 0.95,
    "reason": "Legal thriller turned perverse vendetta in post-reform courtroom"
  },
  {
    "movieId": 204,
    "score": 0.92,
    "reason": "Time-shifting fugitive’s moral haze questions destiny’s bitter cost"
  },
  {
    "movieId": 379,
    "score": 0.9,
    "reason": "Demonic ambush unleashes systematic terror on unsuspecting motel"
  },
  {
    "movieId": 445,
    "score": 0.88,
    "reason": "Classic body-snatching terror reimagined with grim procedural precision"
  },
  {
    "movieId": 588,
    "score": 0.85,
    "reason": "Kidnapping crusade unravels town’s darkest secrets in methodical fury"
  },
  {
    "movieId": 715,
    "score": 0.82,
    "reason": "Marital breakdown exposed to surgical, vengeful dissection of souls"
  },
  {
    "movieId": 672,
    "score": 0.78,
    "reason": "Urban legend incarnate stalks city streets in relentless moral gray"
  },
  {
    "movieId": 163,
    "score": 0.75,
    "reason": "Diamond heist spiral reveals lethal family secrets in cold vengeance"
  },
  {
    "movieId": 1279,
    "score": 0.7,
    "reason": "Blasting conspirators in searing Alaskan wilderness of moral breakdown"
  }
]